lm_api/__init__.py
lm_api/api/__init__.py
lm_api/api/cruds/__init__.py
lm_api/api/cruds/booking.py
lm_api/api/cruds/cluster_status.py
lm_api/api/cruds/configuration.py
lm_api/api/cruds/feature.py
lm_api/api/cruds/generic.py
lm_api/api/models/__init__.py
lm_api/api/models/booking.py
lm_api/api/models/cluster_status.py
lm_api/api/models/configuration.py
lm_api/api/models/crud_base.py
lm_api/api/models/feature.py
lm_api/api/models/job.py
lm_api/api/models/license_server.py
lm_api/api/models/product.py
lm_api/api/routes/__init__.py
lm_api/api/routes/bookings.py
lm_api/api/routes/cluster_statuses.py
lm_api/api/routes/configurations.py
lm_api/api/routes/features.py
lm_api/api/routes/jobs.py
lm_api/api/routes/license_servers.py
lm_api/api/routes/products.py
lm_api/api/schemas/__init__.py
lm_api/api/schemas/base.py
lm_api/api/schemas/booking.py
lm_api/api/schemas/cluster_status.py
lm_api/api/schemas/configuration.py
lm_api/api/schemas/feature.py
lm_api/api/schemas/job.py
lm_api/api/schemas/license_server.py
lm_api/api/schemas/product.py
lm_api/config.py
lm_api/constants.py
lm_api/database.py
lm_api/main.py
lm_api/permissions.py
lm_api/security.py
lm_api/version.py
license_manager_backend-4.5.0.dist-info/METADATA
license_manager_backend-4.5.0.dist-info/WHEEL
license_manager_backend-4.5.0.dist-info/RECORD
