Metadata-Version: 2.4
Name: license-manager-backend
Version: 4.5.0
Summary: Provides an API for managing license data
License: MIT
Author: OmniVector Solutions
Author-email: info@omnivector.solutions
Requires-Python: >=3.12,<4.0
Classifier: License :: OSI Approved :: MIT License
Classifier: Programming Language :: Python :: 3
Classifier: Programming Language :: Python :: 3.12
Classifier: Programming Language :: Python :: 3.13
Classifier: Programming Language :: Python :: 3.14
Requires-Dist: SQLAlchemy-Utils (>=0.42.0,<0.43.0)
Requires-Dist: SQLAlchemy[mypy] (>=2.0.43,<3.0.0)
Requires-Dist: armasec (>=3.0.2,<4.0.0)
Requires-Dist: asyncpg (>=0.30.0,<0.31.0)
Requires-Dist: fastapi[all] (>=0.116.2,<0.117.0)
Requires-Dist: greenlet (>=3.2.4,<4.0.0)
Requires-Dist: inflection (>=0.5.1,<0.6.0)
Requires-Dist: loguru (>=0.7.3,<0.8.0)
Requires-Dist: pendulum[test] (>=3.1.0,<4.0.0)
Requires-Dist: psycopg2 (>=2.9.10,<3.0.0)
Requires-Dist: py-buzz (==7.3.0)
Requires-Dist: pydantic-extra-types (>=2.10.5,<3.0.0)
Requires-Dist: pydantic-settings (>=2.10.1,<3.0.0)
Requires-Dist: pydantic[email] (>=2.11.9,<3.0.0)
Requires-Dist: python-dotenv (>=1.1.1,<2.0.0)
Requires-Dist: sentry-sdk (==2.38.0)
Requires-Dist: toml (>=0.10.2,<0.11.0)
Requires-Dist: uvicorn (>=0.35.0,<0.36.0)
Requires-Dist: yarl (>=1.20.1,<2.0.0)
Project-URL: Documentation, https://omnivector-solutions.github.io/license-manager/
Project-URL: Repository, https://github.com/omnivector-solutions/license-manager
